Workbook

Sheet Assumption
A1: SMART HOME INVENTORY
A2: Key Assumptions
A3: Unit: VND
A4: Chỉ số | B4: Giá trị | C4: Ghi chú
A5: Premium Price (VNĐ/tháng) | B5: 29000 | C5: Khảo sát WTP 20,000-50,000đ
A6: Family Price (VNĐ/tháng) | B6: 59000 | C6: 5 thành viên, chia sẻ dữ liệu
A7: Micro-POS Price (VNĐ/tháng) | B7: 149000 | C7: Khảo sát chủ cửa hàng
A8: Affiliate Commission Rate | B8: 0.05 | C8: Shopee 1-10%, TikTok 2-15%
A9: Affiliate Avg Order Value | B9: 200000 | C9: Giá trị đơn hàng trung bình
A10: Affiliate CTR (N1) | B10: 0.02 | C10: CTR trung bình năm đầu
A11: Affiliate CTR (N2) | B11: 0.03 | C11: CTR trung bình năm 2
A12: Affiliate CTR (N3) | B12: 0.05 | C12: CTR trung bình năm 3
A13: AI Cost Free User (VNĐ/th) | B13: 1300 | C13: ~15 AI voice requests/tháng (Google STT + Gemini Flash)
A14: AI Cost Premium User (VNĐ/th) | B14: 4000 | C14: ~60 AI voice requests/tháng
A15: AI Cost Family User (VNĐ/th) | B15: 6500 | C15: ~100 AI voice requests/tháng (5 thành viên)
A16: AI Cost MicroPOS (VNĐ/th) | B16: 11500 | C16: ~180 AI voice requests/store/tháng
... A27: Churn Rate N3 | B27: 0.05 | C27: Family Sharing + gamification

Sheet Cost Structure
A1: SMART HOME INVENTORY - Cost Structure
A2: Unit: VND — Tự động tính từ Revenue và Assumption
A3: Items | B3: Q1/2027 | C3: Q2/2027 | D3: Q3/2027 | E3: Q4/2027 | F3: Q1/2028 | G3: Q2/2028 | H3: Q3/2028 | I3: Q4/2028 | J3: Q1/2029 | K3: Q2/2029 | L3: Q3/2029 | M3: Q4/2029
A4: COST OF GOODS SOLD
A5: AI API (STT + Gemini) | B5: {=(Revenue!B6:M6*Assumption!$B$13 + Revenue!B7:M7*Assumption!$B$14 + Revenue!B8:M8*Assumption!$B$15 + Revenue!B9:M9*Assumption!$B$16) * 3} -> 297900 | C5: 892500 | D5: 1653300 | E5: 2527500 | F5: 4783200 | G5: 8234100 | H5: 12574800 | I5: 19063800 | J5: 27438000 | K5: 38054400 | L5: 53525700 | M5: 76329000
A6: Cloud & Hosting | B6: =Assumption!$B$17*1*3 -> 3000000 | C6: =Assumption!$B$17*1*3 -> 3000000 | D6: =Assumption!$B$17*1*3 -> 3000000 | E6: =Assumption!$B$17*1*3 -> 3000000 | F6: =Assumption!$B$17*1.15*3 -> 3450000 | G6: =Assumption!$B$17*1.3*3 -> 3900000 | H6: =Assumption!$B$17*1.45*3 -> 4350000 | I6: =Assumption!$B$17*1.6*3 -> 4800000 | J6: =Assumption!$B$17*1.75*3 -> 5250000 | K6: =Assumption!$B$17*1.9*3 -> 5700000 | L6: =Assumption!$B$17*2.05*3 -> 6150000 | M6: =Assumption!$B$17*2.2*3 -> 6600000
A7: SMS & Notification API | B7: =Assumption!$B$18*3 -> 300000 | C7: =Assumption!$B$18*3 -> 300000 | D7: =Assumption!$B$18*3 -> 300000 | E7: =Assumption!$B$18*3 -> 300000 | F7: =Assumption!$B$18*3 -> 300000 | G7: =Assumption!$B$18*3 -> 300000 | H7: =Assumption!$B$18*3 -> 300000 | I7: =Assumption!$B$18*3 -> 300000 | ... M7: =Assumption!$B$18*3 -> 300000
A8: Payment Gateway Fee | B8: =Revenue!B22 * Assumption!$B$20 -> 10297.5 | C8: =Revenue!C22 * Assumption!$B$20 -> 56610 | D8: =Revenue!D22 * Assumption!$B$20 -> 147390 | E8: =Revenue!E22 * Assumption!$B$20 -> 280102.5 | F8: =Revenue!F22 * Assumption!$B$20 -> 507498.75 | G8: =Revenue!G22 * Assumption!$B$20 -> 901743.75 | H8: =Revenue!H22 * Assumption!$B$20 -> 1501098.8 | I8: =Revenue!I22 * Assumption!$B$20 -> 2345932.5 | ... M8: =Revenue!M22 * Assumption!$B$20 -> 10227619
A9: Store Fee (Apple/Google 15%) | B9: =Revenue!B13*Assumption!$B$19 -> 59175 | C9: =Revenue!C13*Assumption!$B$19 -> 330300 | D9: =Revenue!D13*Assumption!$B$19 -> 866250 | E9: =Revenue!E13*Assumption!$B$19 -> 1653750 | F9: =Revenue!F13*Assumption!$B$19 -> 2976075 | G9: =Revenue!G13*Assumption!$B$19 -> 5287950 | H9: =Revenue!H13*Assumption!$B$19 -> 8818875 | I9: =Revenue!I13*Assumption!$B$19 -> 13799250 | ... M9: =Revenue!M13*Assumption!$B$19 -> 59602500
A10: Total COGS | B10: =SUM(B5:B9) -> 3667372.5 | C10: =SUM(C5:C9) -> 4579410 | D10: =SUM(D5:D9) -> 5966940 | E10: =SUM(E5:E9) -> 7761352.5 | F10: =SUM(F5:F9) -> 12016774 | G10: =SUM(G5:G9) -> 18623794 | H10: =SUM(H5:H9) -> 27544774 | I10: =SUM(I5:I9) -> 40308982 | ... M10: =SUM(M5:M9) -> 1.5305912e+08
A12: OPERATING EXPENSES
A13: Marketing & Promotion | B13: 3000000 | C13: 3000000 | D13: 3000000 | E13: 3000000 | F13: 13000000 | G13: 13000000 | H13: 13000000 | I13: 13000000 | J13: 15000000 | K13: 15000000 | L13: 15000000 | M13: 15000000
A14: Token Stipend (Cash) | B14: 900000 | C14: 900000 | D14: 900000 | E14: 900000 | F14: 1080000 | G14: 1080000 | H14: 1080000 | I14: 1080000 | J14: 1260000 | K14: 1260000 | L14: 1260000 | M14: 1260000
A15: Maintenance & Monitoring | B15: 1000000 | C15: 1000000 | D15: 1000000 | E15: 1500000 | F15: 1500000 | G15: 1500000 | H15: 2000000 | I15: 2000000 | J15: 2000000 | K15: 2500000 | L15: 2500000 | M15: 2500000
A16: Deferred Salary (Lương treo) | B16: 18000000 | C16: 18000000 | D16: 18000000 | E16: 18000000 | F16: 27000000 | G16: 27000000 | H16: 27000000 | I16: 27000000 | J16: 36000000 | K16: 36000000 | L16: 36000000 | M16: 36000000
A17: Total OPEX (Full Accrual) | B17: =SUM(B13:B16) -> 22900000 | C17: =SUM(C13:C16) -> 22900000 | D17: =SUM(D13:D16) -> 22900000 | E17: =SUM(E13:E16) -> 23400000 | F17: =SUM(F13:F16) -> 42580000 | G17: =SUM(G13:G16) -> 42580000 | H17: =SUM(H13:H16) -> 43080000 | I17: =SUM(I13:I16) -> 43080000 | ... M17: =SUM(M13:M16) -> 54760000
A18: Total OPEX (Cash only) | B18: =B17-B16 -> 4900000 | C18: =C17-C16 -> 4900000 | D18: =D17-D16 -> 4900000 | E18: =E17-E16 -> 5400000 | F18: =F17-F16 -> 15580000 | G18: =G17-G16 -> 15580000 | H18: =H17-H16 -> 16080000 | I18: =I17-I16 -> 16080000 | ... M18: =M17-M16 -> 18760000
A19: TOTAL COST & EXPENSES | B19: =B10+B17 -> 26567372 | C19: =C10+C17 -> 27479410 | D19: =D10+D17 -> 28866940 | E19: =E10+E17 -> 31161352 | F19: =F10+F17 -> 54596774 | G19: =G10+G17 -> 61203794 | H19: =H10+H17 -> 70624774 | I19: =I10+I17 -> 83388982 | ... M19: =M10+M17 -> 2.0781912e+08

Sheet Revenue
A1: SMART HOME INVENTORY - Revenue
A2: Unit: VND | Điều chỉnh số user tại đây, các ô khác tự tính
A4: REVENUE STREAM 1: Subscription
A5: INDEX | B5: Q1/2027 | C5: Q2/2027 | D5: Q3/2027 | E5: Q4/2027 | F5: Q1/2028 | G5: Q2/2028 | H5: Q3/2028 | I5: Q4/2028 | J5: Q1/2029 | K5: Q2/2029 | L5: Q3/2029 | M5: Q4/2029
A6: Free Users | B6: 51 | C6: 125 | D6: 197 | E6: 250 | F6: 498 | G6: 819 | H6: 1107 | I6: 1617 | J6: 2170 | K6: 2796 | L6: 3863 | M6: 5510
A7: Premium Users | B7: 5 | C7: 15 | D7: 35 | E7: 60 | F7: 120 | G7: 220 | H7: 380 | I7: 600 | J7: 900 | K7: 1300 | L7: 1900 | M7: 2800
A8: Family Users | B8: 2 | C8: 8 | D8: 15 | E8: 25 | F8: 40 | G8: 70 | H8: 110 | I8: 170 | J8: 260 | K8: 380 | L8: 520 | M8: 700
A9: Micro-POS Users | B9: 0 | C9: 2 | D9: 5 | E9: 10 | F9: 18 | G9: 30 | H9: 45 | I9: 65 | J9: 90 | K9: 120 | L9: 160 | M9: 220
A10: Premium Revenue | B10: =B7/2 * Assumption!$B$5 * 3 -> 217500 | C10: =(B7+C7)/2 * Assumption!$B$5 * 3 -> 870000 | D10: =(C7+D7)/2 * Assumption!$B$5 * 3 -> 2175000 | E10: =(D7+E7)/2 * Assumption!$B$5 * 3 -> 4132500 | F10: =(E7+F7)/2 * Assumption!$B$5 * 3 -> 7830000 | G10: =(F7+G7)/2 * Assumption!$B$5 * 3 -> 14790000 | H10: =(G7+H7)/2 * Assumption!$B$5 * 3 -> 26100000 | I10: =(H7+I7)/2 * Assumption!$B$5 * 3 -> 42630000 | J10: =(I7+J7)/2 * Assumption!$B$5 * 3 -> 65250000 | ... M10: =(L7+M7)/2 * Assumption!$B$5 * 3 -> 204450000
A11: Family Revenue | B11: =B8/2 * Assumption!$B$6 * 3 -> 177000 | C11: =(B8+C8)/2 * Assumption!$B$6 * 3 -> 885000 | D11: =(C8+D8)/2 * Assumption!$B$6 * 3 -> 2035500 | E11: =(D8+E8)/2 * Assumption!$B$6 * 3 -> 3540000 | F11: =(E8+F8)/2 * Assumption!$B$6 * 3 -> 5752500 | G11: =(F8+G8)/2 * Assumption!$B$6 * 3 -> 9735000 | H11: =(G8+H8)/2 * Assumption!$B$6 * 3 -> 15930000 | I11: =(H8+I8)/2 * Assumption!$B$6 * 3 -> 24780000 | J11: =(I8+J8)/2 * Assumption!$B$6 * 3 -> 38055000 | ... M11: =(L8+M8)/2 * Assumption!$B$6 * 3 -> 107970000
A12: Micro-POS Revenue | B12: =B9/2 * Assumption!$B$7 * 3 -> 0 | C12: =(B9+C9)/2 * Assumption!$B$7 * 3 -> 447000 | D12: =(C9+D9)/2 * Assumption!$B$7 * 3 -> 1564500 | E12: =(D9+E9)/2 * Assumption!$B$7 * 3 -> 3352500 | F12: =(E9+F9)/2 * Assumption!$B$7 * 3 -> 6258000 | G12: =(F9+G9)/2 * Assumption!$B$7 * 3 -> 10728000 | H12: =(G9+H9)/2 * Assumption!$B$7 * 3 -> 16762500 | I12: =(H9+I9)/2 * Assumption!$B$7 * 3 -> 24585000 | J12: =(I9+J9)/2 * Assumption!$B$7 * 3 -> 34642500 | ... M12: =(L9+M9)/2 * Assumption!$B$7 * 3 -> 84930000
A13: Total Subscription Revenue | B13: =SUM(B10:B12) -> 394500 | C13: =SUM(C10:C12) -> 2202000 | D13: =SUM(D10:D12) -> 5775000 | E13: =SUM(E10:E12) -> 11025000 | F13: =SUM(F10:F12) -> 19840500 | G13: =SUM(G10:G12) -> 35253000 | H13: =SUM(H10:H12) -> 58792500 | I13: =SUM(I10:I12) -> 91995000 | ... M13: =SUM(M10:M12) -> 397350000
A16: REVENUE STREAM 2: Affiliate Marketing
A17: INDEX | B17: Q1/2027 | C17: Q2/2027 | D17: Q3/2027 | E17: Q4/2027 | F17: Q1/2028 | G17: Q2/2028 | H17: Q3/2028 | I17: Q4/2028 | J17: Q1/2029 | K17: Q2/2029 | L17: Q3/2029 | M17: Q4/2029
A18: Affiliate Revenue | B18: =(B7+B8+B9+B6)/2 * Assumption!$B$9 * Assumption!$B$8 * Assumption!$B$10 * 3 -> 17400 | C18: =(B7+B8+B9+C7+C8+C9+C6+B6)/2 * Assumption!$B$9 * Assumption!$B$8 * Assumption!$B$10 * 3 -> 62400 | D18: =(C7+C8+C9+D7+D8+D9+D6+C6)/2 * Assumption!$B$9 * Assumption!$B$8 * Assumption!$B$10 * 3 -> 120600 | E18: =(D7+D8+D9+E7+E8+E9+E6+D6)/2 * Assumption!$B$9 * Assumption!$B$8 * Assumption!$B$10 * 3 -> 179100 | F18: =(E7+E8+E9+F7+F8+F9+F6+E6)/2 * Assumption!$B$9 * Assumption!$B$8 * Assumption!$B$11 * 3 -> 459450 | G18: =(F7+F8+F9+G7+G8+G9+G6+F6)/2 * Assumption!$B$9 * Assumption!$B$8 * Assumption!$B$11 * 3 -> 816750 | H18: =(G7+G8+G9+H7+H8+H9+H6+G6)/2 * Assumption!$B$9 * Assumption!$B$8 * Assumption!$B$11 * 3 -> 1251450 | I18: =(H7+H8+H9+I7+I8+I9+I6+H6)/2 * Assumption!$B$9 * Assumption!$B$8 * Assumption!$B$11 * 3 -> 1842300 | J18: =(I7+I8+I9+J7+J8+J9+J6+I6)/2 * Assumption!$B$9 * Assumption!$B$8 * Assumption!$B$12 * 3 -> 4404000 | K18: =(J7+J8+J9+K7+K8+K9+K6+J6)/2 * Assumption!$B$9 * Assumption!$B$8 * Assumption!$B$12 * 3 -> 6012000 | L18: =(K7+K8+K9+L7+L8+L9+L6+K6)/2 * Assumption!$B$9 * Assumption!$B$8 * Assumption!$B$12 * 3 -> 8279250 | M18: =(L7+L8+L9+M7+M8+M9+M6+L6)/2 * Assumption!$B$9 * Assumption!$B$8 * Assumption!$B$12 * 3 -> 11754750
A20: GRAND TOTAL REVENUE
A21: INDEX | B21: Q1/2027 | C21: Q2/2027 | D21: Q3/2027 | E21: Q4/2027 | F21: Q1/2028 | G21: Q2/2028 | H21: Q3/2028 | I21: Q4/2028 | J21: Q1/2029 | K21: Q2/2029 | L21: Q3/2029 | M21: Q4/2029
A22: Total Revenue | B22: =SUM(B13,B18) -> 411900 | C22: =SUM(C13,C18) -> 2264400 | D22: =SUM(D13,D18) -> 5895600 | E22: =SUM(E13,E18) -> 11204100 | F22: =SUM(F13,F18) -> 20299950 | G22: =SUM(G13,G18) -> 36069750 | H22: =SUM(H13,H18) -> 60043950 | I22: =SUM(I13,I18) -> 93837300 | ... M22: =SUM(M13,M18) -> 409104750

Sheet P&L Statement
A1: SMART HOME INVENTORY
A2: Profit and Loss Statement
A3: Unit: VND — Tất cả đều là công thức
A4: Chỉ tiêu | B4: Q1/2027 | C4: Q2/2027 | D4: Q3/2027 | E4: Q4/2027 | F4: Q1/2028 | G4: Q2/2028 | H4: Q3/2028 | I4: Q4/2028 | J4: Q1/2029 | K4: Q2/2029 | L4: Q3/2029 | M4: Q4/2029
A5: Total Revenue | B5: =Revenue!B22 -> 411900 | C5: =Revenue!C22 -> 2264400 | D5: =Revenue!D22 -> 5895600 | E5: =Revenue!E22 -> 11204100 | F5: =Revenue!F22 -> 20299950 | G5: =Revenue!G22 -> 36069750 | H5: =Revenue!H22 -> 60043950 | I5: =Revenue!I22 -> 93837300 | ... M5: =Revenue!M22 -> 409104750
A7: Cost of Goods Sold | B7: ='Cost Structure'!B10 -> 3667372.5 | C7: ='Cost Structure'!C10 -> 4579410 | D7: ='Cost Structure'!D10 -> 5966940 | E7: ='Cost Structure'!E10 -> 7761352.5 | F7: ='Cost Structure'!F10 -> 12016774 | G7: ='Cost Structure'!G10 -> 18623794 | H7: ='Cost Structure'!H10 -> 27544774 | I7: ='Cost Structure'!I10 -> 40308982 | ... M7: ='Cost Structure'!M10 -> 1.5305912e+08
A8: Gross Profit | B8: =B5-B7 -> -3255472.5 | C8: =C5-C7 -> -2315010 | D8: =D5-D7 -> -71340 | E8: =E5-E7 -> 3442747.5 | F8: =F5-F7 -> 8283176.2 | G8: =G5-G7 -> 17445956 | H8: =H5-H7 -> 32499176 | I8: =I5-I7 -> 53528318 | ... M8: =M5-M7 -> 2.5604563e+08
A9: Gross Margin % | B9: =IF(B5>0,B8/B5,"N/A") -> -7.9035506 | C9: =IF(C5>0,C8/C5,"N/A") -> -1.0223503 | D9: =IF(D5>0,D8/D5,"N/A") -> -0.01210055 | E9: =IF(E5>0,E8/E5,"N/A") -> 0.30727568 | F9: =IF(F5>0,F8/F5,"N/A") -> 0.40803924 | G9: =IF(G5>0,G8/G5,"N/A") -> 0.48367278 | H9: =IF(H5>0,H8/H5,"N/A") -> 0.54125647 | I9: =IF(I5>0,I8/I5,"N/A") -> 0.57043753 | ... M9: =IF(M5>0,M8/M5,"N/A") -> 0.62586815
A11: Operating Expenses (Cash) | B11: ='Cost Structure'!B18 -> 4900000 | C11: ='Cost Structure'!C18 -> 4900000 | D11: ='Cost Structure'!D18 -> 4900000 | E11: ='Cost Structure'!E18 -> 5400000 | F11: ='Cost Structure'!F18 -> 15580000 | G11: ='Cost Structure'!G18 -> 15580000 | H11: ='Cost Structure'!H18 -> 16080000 | I11: ='Cost Structure'!I18 -> 16080000 | ... M11: ='Cost Structure'!M18 -> 18760000
A13: EBIT (Cash) | B13: =B8-B11 -> -8155472.5 | C13: =C8-C11 -> -7215010 | D13: =D8-D11 -> -4971340 | E13: =E8-E11 -> -1957252.5 | F13: =F8-F11 -> -7296823.8 | G13: =G8-G11 -> 1865956.2 | H13: =H8-H11 -> 16419176 | I13: =I8-I11 -> 37448318 | ... M13: =M8-M11 -> 2.3728563e+08
A15: EBIT (Full Accrual) | B15: =B8-'Cost Structure'!B17 -> -26155472 | C15: =C8-'Cost Structure'!C17 -> -25215010 | D15: =D8-'Cost Structure'!D17 -> -22971340 | E15: =E8-'Cost Structure'!E17 -> -19957252 | F15: =F8-'Cost Structure'!F17 -> -34296824 | G15: =G8-'Cost Structure'!G17 -> -25134044 | H15: =H8-'Cost Structure'!H17 -> -10580824 | I15: =I8-'Cost Structure'!I17 -> 10448318 | ... M15: =M8-'Cost Structure'!M17 -> 2.0128563e+08
A17: Corporate Tax (20%) | B17: =IF(B15>0,B15*Assumption!$B$24,0) -> 0 | C17: =IF(C15>0,C15*Assumption!$B$24,0) -> 0 | D17: =IF(D15>0,D15*Assumption!$B$24,0) -> 0 | E17: =IF(E15>0,E15*Assumption!$B$24,0) -> 0 | F17: =IF(F15>0,F15*Assumption!$B$24,0) -> 0 | G17: =IF(G15>0,G15*Assumption!$B$24,0) -> 0 | H17: =IF(H15>0,H15*Assumption!$B$24,0) -> 0 | I17: =IF(I15>0,I15*Assumption!$B$24,0) -> 0 | ... M17: =IF(M15>0,M15*Assumption!$B$24,0) -> 0
A19: Net Profit / (Loss) Full Accrual | B19: =B15-B17 -> -26155472 | C19: =C15-C17 -> -25215010 | D19: =D15-D17 -> -22971340 | E19: =E15-E17 -> -19957252 | F19: =F15-F17 -> -34296824 | G19: =G15-G17 -> -25134044 | H19: =H15-H17 -> -10580824 | I19: =I15-I17 -> 10448318 | ... M19: =M15-M17 -> 2.0128563e+08
A20: Net Margin % | B20: =IF(B5>0,B19/B5,"N/A") -> -63.499569 | C20: =IF(C5>0,C19/C5,"N/A") -> -11.135405 | D20: =IF(D5>0,D19/D5,"N/A") -> -3.8963532 | E20: =IF(E5>0,E19/E5,"N/A") -> -1.7812455 | F20: =IF(F5>0,F19/F5,"N/A") -> -1.6895029 | G20: =IF(G5>0,G19/G5,"N/A") -> -0.6968178 | H20: =IF(H5>0,H19/H5,"N/A") -> -0.17621798 | I20: =IF(I5>0,I19/I5,"N/A") -> 0.11134504 | ... M20: =IF(M5>0,M19/M5,"N/A") -> 0.4920149
A22: 3-YEAR TOTAL NET PROFIT/LOSS | B22: =SUM(B19:M19) -> 2.7524126e+08
A23: Cumulative Net Profit (Cash) | B23: =B13 -> -8155472.5 | C23: =B23+C13 -> -15370482 | D23: =C23+D13 -> -20341822 | E23: =D23+E13 -> -22299075 | F23: =E23+F13 -> -29595899 | G23: =F23+G13 -> -27729942 | H23: =G23+H13 -> -11310766 | I23: =H23+I13 -> 26137551 | J23: =I23+J13 -> 92990139 | ... M23: =L23+M13 -> 5.9924126e+08

Sheet Fundraising
A1: SMART HOME INVENTORY
A2: Fundraising Plan
A3: Unit: VND
A5: Khoản mục | B5: Năm 1 (2027) | C5: Năm 2 (2028) | D5: Năm 3 (2029)
A6: Planned Revenue | B6: =SUM('P&L Statement'!B5:E5) -> 19776000 | C6: =SUM('P&L Statement'!F5:I5) -> 210250950 | D6: =SUM('P&L Statement'!J5:M5) -> 1046452500
A7: Planned COGS | B7: =SUM('Cost Structure'!B10:E10) -> 21975075 | C7: =SUM('Cost Structure'!F10:I10) -> 98494324 | D7: =SUM('Cost Structure'!J10:M10) -> 3.9880879e+08
A8: Planned OPEX (Cash) | B8: =SUM('Cost Structure'!B18:E18) -> 20100000 | C8: =SUM('Cost Structure'!F18:I18) -> 63320000 | D8: =SUM('Cost Structure'!J18:M18) -> 74540000
A9: Net Cash Flow (Annual) | B9: =B6-B7-B8 -> -22299075 | C9: =C6-C7-C8 -> 48436626 | D9: =D6-D7-D8 -> 5.7310371e+08
A11: 3-Year Total Cash Flow | B11: =SUM(B9:D9) -> 5.9924126e+08
A13: FUNDING SOURCES
A14: Nguồn vốn | B14: Số tiền | C14: Loại | D14: Ghi chú
A15: Founder Contribution (6 người) | B15: 6000000 | C15: Equity | D15: 1,000,000đ/người
A16: FPT Education Grant | B16: 50000000 | C16: Non-dilutive | D16: Đang chờ
A18: Tổng vốn huy động | B18: =SUM(B15:B16) -> 56000000
A19: Chi phí cash Năm 1 | B19: =B7+B8 -> 42075075
A20: Thặng dư/Thiếu hụt | B20: =B18-B19 -> 13924925
A22: USE OF FUNDS (Năm 1)
A23: Hạng mục | B23: Tỷ lệ | C23: Số tiền | D23: Giải thích
A24: Marketing & User Acquisition | B24: =C24/$C$28 -> 0.21428571 | C24: =SUM('Cost Structure'!B13:E13) -> 12000000 | D24: KOC, TikTok Ads, Referral
A25: Product & Tech | B25: =C25/$C$28 -> 0.41198571 | C25: =SUM('Cost Structure'!B5:E7, 'Cost Structure'!B15:E15) -> 23071200 | D25: AI API, Cloud, Database
A26: Operation & Admin | B26: =C26/$C$28 -> 0.1250692 | C26: =SUM('Cost Structure'!B8:E9, 'Cost Structure'!B14:E14) -> 7003875 | D26: Domain, tool, stipend
A27: Dự phòng | B27: =C27/$C$28 -> 0.24865937 | C27: =B18-SUM(C24:C26) -> 13924925 | D27: Rủi ro phát sinh
A28: Tổng | B28: 1 | C28: =SUM(C24:C27) -> 56000000

Sheet Unit Economics
A1: SMART HOME INVENTORY
A2: Unit Economics (CAC / LTV / Breakeven)
A4: Chỉ số | B4: Năm 1 | C4: Năm 2 | D4: Năm 3
A5: Tổng Marketing | B5: =SUM('Cost Structure'!B13:E13) -> 12000000 | C5: =SUM('Cost Structure'!F13:I13) -> 52000000 | D5: =SUM('Cost Structure'!J13:M13) -> 60000000
A6: User trả phí mới (Premium+Family+Micro) | B6: =SUM(Revenue!B7:E9) -> 182 | C6: =SUM(Revenue!F7:I9) -> 1868 | D6: =SUM(Revenue!J7:M9) -> 9350
A7: CAC (VNĐ) = Marketing / New Paid | B7: =IF(B6>0,B5/B6,0) -> 65934.066 | C7: =IF(C6>0,C5/C6,0) -> 27837.259 | D7: =IF(D6>0,D5/D6,0) -> 6417.1123
A8: ARPU trung bình (VNĐ/tháng) | B8: =SUM(Revenue!B13:E13) / SUM(Revenue!B7:E9) / 3 -> 35524.725 | C8: =SUM(Revenue!F13:I13) / SUM(Revenue!F7:I9) / 3 -> 36738.223 | D8: =SUM(Revenue!J13:M13) / SUM(Revenue!J7:M9) / 3 -> 36221.123
A9: Churn rate/tháng | B9: =Assumption!B25 -> 0.09 | C9: =Assumption!B26 -> 0.07 | D9: =Assumption!B27 -> 0.05
A10: Lifetime (tháng) = 1/Churn | B10: =IF(B9>0,1/B9,0) -> 11.111111 | C10: =IF(C9>0,1/C9,0) -> 14.285714 | D10: =IF(D9>0,1/D9,0) -> 20
A11: LTV = (ARPU − Chi phí AI − Phí Store 15% − Phí thanh toán 3%) × Lifetime | B11: =(B8 - SUM('Cost Structure'!B5:E5)/SUM(Revenue!B7:E9)/3 - B8*Assumption!$B$19 - B8*Assumption!$B$20) * B10 -> 216339.29 | C11: =(C8 - SUM('Cost Structure'!F5:I5)/SUM(Revenue!F7:I9)/3 - C8*Assumption!$B$19 - C8*Assumption!$B$20) * C10 -> 319149.4 | D11: =(D8 - SUM('Cost Structure'!J5:M5)/SUM(Revenue!J7:M9)/3 - D8*Assumption!$B$19 - D8*Assumption!$B$20) * D10 -> 458363.61
A12: LTV / CAC Ratio | B12: =IF(B7>0,B11/B7,0) -> 3.2811458 | C12: =IF(C7>0,C11/C7,0) -> 11.464828 | D12: =IF(D7>0,D11/D7,0) -> 71.428329
A14: BREAKEVEN ANALYSIS
A15: Công thức: BE_Users = Cash_FC / (ARPU - Var_cost)
A16: Kịch bản | B16: FC cash/tháng | C16: ARPU | D16: Var/user | E16: Users cần
A17: Bi quan (churn 12%) | B17: 14000000 | C17: 20000 | D17: 1200 | E17: =ROUNDUP(B17/(C17-D17),0) -> 745
A18: Cơ sở (churn 10%) | B18: 14833333 | C18: 32000 | D18: 1200 | E18: =ROUNDUP(B18/(C18-D18),0) -> 482
A19: Lạc quan (churn 5%) | B19: 16000000 | C19: 50000 | D19: 1200 | E19: =ROUNDUP(B19/(C19-D19),0) -> 328

Sheet Valuation
A1: SMART HOME INVENTORY
A2: Valuation (Comparables Method - Sum-of-Parts)
A3: Unit: VND
A5: 1. DOANH THU NĂM 3 (2029) THEO NGÁCH — cơ sở Sum-of-Parts
A6: Dòng doanh thu | B6: Doanh thu Năm 3 - 2029 (VND) | C6: Ngách tương ứng (dùng để chọn multiple)
A7: B2C Subscription (Premium + Family) | B7: =SUM(Revenue!J10:M11) -> 786915000 | C7: Consumer subscription app
A8: B2B Micro-POS | B8: =SUM(Revenue!J12:M12) -> 229087500 | C8: Vertical SaaS - Retail/POS
A9: Affiliate Marketing | B9: =SUM(Revenue!J18:M18) -> 30450000 | C9: Commission / Ads-like revenue
A10: TOTAL Doanh thu Năm 3 | B10: =SUM(B7:B9) -> 1046452500 | C10: ✓ Khớp Revenue sheet
A12: 2. EV/REVENUE MULTIPLE THEO NGÁCH (sourced — sát ngách hơn SaaS chung toàn cầu)
A13: Ngách | B13: Thận trọng | C13: Cơ sở | D13: Lạc quan | E13: Nguồn / Ghi chú
A14: B2C Subscription | B14: 1.5 | C14: 2 | D14: 3 | E14: Micro-SaaS sub-$1M ARR: 2.5-4x ARR (CT Acquisitions, 2026); chiết khấu thêm cho B2C do churn cao/LTV thấp hơn B2B
A15: B2B Micro-POS | B15: 2.5 | C15: 3.5 | D15: 5 | E15: Vertical SaaS Retail/Restaurant: 3-6x ARR (SaaS Capital Index + KeyBanc KBCM Survey 2025, Q1 2026); giảm cho pre-seed
A16: Affiliate Marketing | B16: 0.5 | C16: 1 | D16: 1.5 | E16: Thấp hơn SaaS; gần agency/ads multiple (~2.75x - Newfrontier Funding); chiết khấu mạnh do quy mô nhỏ + rủi ro cao
A18: 3. ĐỊNH GIÁ CHÍNH THỨC — SUM-OF-PARTS COMPARABLES
A19: Kịch bản | B19: B2C EV (VND) | C19: Micro-POS EV (VND) | D19: Affiliate EV (VND) | E19: TOTAL Implied EV (VND)
A20: Thận trọng | B20: =B7*B14 -> 1180372500 | C20: =B8*B15 -> 572718750 | D20: =B9*B16 -> 15225000 | E20: =SUM(B20:D20) -> 1768316250
A21: Cơ sở | B21: =B7*C14 -> 1573830000 | C21: =B8*C15 -> 801806250 | D21: =B9*C16 -> 30450000 | E21: =SUM(B21:D21) -> 2406086250
A22: Lạc quan | B22: =B7*D14 -> 2360745000 | C22: =B8*D15 -> 1145437500 | D22: =B9*D16 -> 45675000 | E22: =SUM(B22:D22) -> 3551857500
A24: GIÁ TRỊ SỬ DỤNG CHO PITCH: Kịch bản 'Cơ sở' (~2,406,086,250 VNĐ) làm pre-money chính thức theo Comparables Method (Sum-of-Parts theo ngách) — không dùng DCF. Berkus (mục 4) chỉ dùng KIỂM TRA CHÉO, không thay thế Comparables.
A26: 4. BERKUS METHOD (Kiểm tra chéo — KHÔNG phải định giá chính thức)
A27: Yếu tố | B27: Giá tối đa | C27: Hệ số | D27: Kết quả
A28: Basic Idea | B28: 500000000 | C28: 0.6 | D28: =B28*C28 -> 300000000
A29: Prototype/MVP | B29: 500000000 | C29: 0.4 | D29: =B29*C29 -> 200000000
A30: Team Quality | B30: 500000000 | C30: 0.7 | D30: =B30*C30 -> 350000000
A31: Strategic Relationships | B31: 500000000 | C31: 0.2 | D31: =B31*C31 -> 100000000
A32: Product Rollout | B32: 500000000 | C32: 0.2 | D32: =B32*C32 -> 100000000
A33: Pre-money (Berkus) | D33: =SUM(D28:D32) -> 1050000000
A35: 5. EQUITY SENSITIVITY (% Equity = Raise / (Pre-money + Raise))
A36: Raise ↓ / Pre-money → | B36: 1.000tỷ | C36: 2.000tỷ | D36: 3.000tỷ | E36: 4.000tỷ
A37: 50.000.000đ | B37: 4,8% | C37: 2,4% | D37: 1,6% | E37: 1,2%
A38: 80.000.000đ | B38: 7,4% | C38: 3,8% | D38: 2,6% | E38: 2,0%
A39: 100.000.000đ | B39: 9,1% | C39: 4,8% | D39: 3,2% | E39: 2,4%

Sheet Sources
A1: SMART HOME INVENTORY
A2: Sources & References
A4: Topic | B4: Nội dung | C4: Link | D4: Ghi chú
A5: ASSUMPTION
B6: Lãng phí B2C: 123.000đ/tháng | D6: Khảo sát 96 người
B7: Thất thoát B2B: 550.000đ/tháng | D7: Khảo sát 15 chủ cửa hàng
B8: WTP B2C: 20.000-50.000đ (39 người) | D8: Khảo sát 111 người
B9: WTP B2B: 100.000-200.000đ (12 người) | D9: Khảo sát 52 chủ cửa hàng
B10: Tăng trưởng Home Tech: 18.7%/năm | C10: https://seller.alibaba.com/blogs/2026/southeast-asia/smart-home-devices/bridging-the-compatibility-chasm | D10: Báo cáo thị trường
A11: TECH COST
B12: Text to speech tool gg | C12: https://cloud.google.com/speech-to-text/pricing?utm_source=chatgpt.com | D12: Text to speech tool gg
B13: Gemini 3.5 Flash pricing | C13: https://ai.google.dev/pricing | D13: Google AI (07/2026)
B14: Firebase Cloud Messaging | C14: https://firebase.google.com/pricing | D14: Firebase free tier
B15: MongoDB Atlas | C15: https://www.mongodb.com/pricing | D15: Free tier up to 512MB
B16: Domain .vn pricing | C16: https://tenten.vn/vi/dang-ky-ten-mien | D16: Các nhà đăng ký tên miền VN
A17: REVENUE
B18: Premium 29.000đ, Family 59.000đ | D18: WTP khảo sát
B19: Micro-POS 149.000đ | D19: So sánh KiotViet 250-490k
B20: Shopee Affiliate 1-10% | C20: https://affiliate.shopee.vn/ | D20: Shopee Affiliate Program
B21: TikTok Shop Affiliate 2-15% | C21: https://seller-vn.tiktok.com/ | D21: TikTok Shop
A22: COMPETITOR
B23: KiotViet: 250.000-490.000đ/tháng | D23: Website KiotViet
B24: NoWaste: không hỗ trợ tiếng Việt | D24: App Store
B25: Sortly: $24/tháng | C25: https://www.sortly.com/pricing/ | D25: Website Sortly
A26: VALUATION
B27: Berkus Method | C27: https://berkus.com/the-berkus-method-valuing-an-early-stage-investment-2/ | D27: Dave Berkus
B28: Scorecard Method | D28: Bill Payne
B29: WACC 15% Pre-seed VN | D29: Tham chiếu thị trường
B30: Thuế TNDN 20% | C30: https://thuvienphapluat.vn/ | D30: Luật Thuế VN
